codeoptimist/yaml/__init__.py
codeoptimist/yaml/main.py
codeoptimist.yaml-0.2.0.dist-info/LICENSE
codeoptimist.yaml-0.2.0.dist-info/METADATA
codeoptimist.yaml-0.2.0.dist-info/NOTICE
codeoptimist.yaml-0.2.0.dist-info/WHEEL
codeoptimist.yaml-0.2.0.dist-info/top_level.txt
codeoptimist.yaml-0.2.0.dist-info/RECORD
